{
  "version": "7",
  "dialect": "postgresql",
  "entries": [
    {
      "idx": 0,
      "version": "7",
      "when": 1773366842053,
      "tag": "0000_tan_prism",
      "breakpoints": true
    },
    {
      "idx": 1,
      "version": "7",
      "when": 1773454574760,
      "tag": "0001_smart_dust",
      "breakpoints": true
    },
    {
      "idx": 2,
      "version": "7",
      "when": 1773608865216,
      "tag": "0002_black_lady_mastermind",
      "breakpoints": true
    },
    {
      "idx": 3,
      "version": "7",
      "when": 1773756471780,
      "tag": "0003_pale_energizer",
      "breakpoints": true
    },
    {
      "idx": 4,
      "version": "7",
      "when": 1773887377313,
      "tag": "0004_late_gateway",
      "breakpoints": true
    }
  ]
}